covid19umbria/__init__.py
covid19umbria/covid19umbria.py
covid19umbria-0.0.6.dist-info/LICENSE
covid19umbria-0.0.6.dist-info/METADATA
covid19umbria-0.0.6.dist-info/WHEEL
covid19umbria-0.0.6.dist-info/top_level.txt
covid19umbria-0.0.6.dist-info/RECORD
