Metadata-Version: 2.1
Name: covid19umbria
Version: 0.0.6
Summary: Covid-19 statistics for Regione Umbria, based on the public API
Home-page: https://github.com/reale/covid19umbria
Author: Roberto Reale
Author-email: roberto@reale.me
License: MIT
Project-URL: Source, https://github.com/reale/covid19umbria
Platform: UNKNOWN
Classifier: Intended Audience :: Developers
Classifier: Topic :: Utilities
Classifier: License :: OSI Approved :: MIT License
Classifier: Programming Language :: Python :: 3
Classifier: Programming Language :: Python :: 3.7
Classifier: Programming Language :: Python :: 3.8
Requires-Python: >=3.6
Requires-Dist: requests
Requires-Dist: beautifulsoup4
Provides-Extra: dev
Requires-Dist: pipenv ; extra == 'dev'
Requires-Dist: pytest ; extra == 'dev'
Requires-Dist: ipdb ; extra == 'dev'
Requires-Dist: pre-commit ; extra == 'dev'
Requires-Dist: black ; extra == 'dev'
